{"label": "resume", "path_img": "resume\\doc_000629.png\n"}
{"label": "email", "path_img": "email\\doc_000046.png\n"}
{"label": "paper", "path_img": "paper\\doc_000240.png\n"}
{"label": "email", "path_img": "email\\doc_000586.png\n"}
{"label": "paper", "path_img": "paper\\doc_000089.png\n"}
{"label": "resume", "path_img": "resume\\doc_000051.png\n"}
{"label": "email", "path_img": "email\\doc_000558.png\n"}
{"label": "paper", "path_img": "paper\\doc_000697.png\n"}
{"label": "resume", "path_img": "resume\\doc_000501.png\n"}
{"label": "resume", "path_img": "resume\\doc_000080.png\n"}
{"label": "paper", "path_img": "paper\\doc_000285.png\n"}
{"label": "resume", "path_img": "resume\\doc_000361.png\n"}
{"label": "paper", "path_img": "paper\\doc_000530.png\n"}
{"label": "resume", "path_img": "resume\\doc_000447.png\n"}
{"label": "resume", "path_img": "resume\\doc_000223.png\n"}
{"label": "resume", "path_img": "resume\\doc_000402.png\n"}
{"label": "email", "path_img": "email\\doc_000042.png\n"}
{"label": "resume", "path_img": "resume\\doc_000476.png\n"}
{"label": "paper", "path_img": "paper\\doc_000250.png\n"}
{"label": "email", "path_img": "email\\doc_000448.png\n"}
{"label": "paper", "path_img": "paper\\doc_000498.png\n"}
{"label": "email", "path_img": "email\\doc_000297.png\n"}
{"label": "resume", "path_img": "resume\\doc_000411.png\n"}
{"label": "paper", "path_img": "paper\\doc_000509.png\n"}
{"label": "paper", "path_img": "paper\\doc_000128.png\n"}
{"label": "paper", "path_img": "paper\\doc_000480.png\n"}
{"label": "resume", "path_img": "resume\\doc_000286.png\n"}
{"label": "resume", "path_img": "resume\\doc_000294.png\n"}
{"label": "resume", "path_img": "resume\\doc_000070.png\n"}
{"label": "paper", "path_img": "paper\\doc_000534.png\n"}
{"label": "resume", "path_img": "resume\\doc_000191.png\n"}
{"label": "resume", "path_img": "resume\\doc_000460.png\n"}
{"label": "paper", "path_img": "paper\\doc_000617.png\n"}
{"label": "resume", "path_img": "resume\\doc_000543.png\n"}
{"label": "paper", "path_img": "paper\\doc_000228.png\n"}
{"label": "paper", "path_img": "paper\\doc_000349.png\n"}
{"label": "email", "path_img": "email\\doc_000111.png\n"}
{"label": "email", "path_img": "email\\doc_000507.png\n"}
{"label": "email", "path_img": "email\\doc_000596.png\n"}
{"label": "email", "path_img": "email\\doc_000278.png\n"}
{"label": "paper", "path_img": "paper\\doc_000756.png\n"}
{"label": "paper", "path_img": "paper\\doc_000045.png\n"}
{"label": "email", "path_img": "email\\doc_000655.png\n"}
{"label": "paper", "path_img": "paper\\doc_000016.png\n"}
{"label": "paper", "path_img": "paper\\doc_000171.png\n"}
{"label": "paper", "path_img": "paper\\doc_000437.png\n"}
{"label": "paper", "path_img": "paper\\doc_000741.png\n"}
{"label": "resume", "path_img": "resume\\doc_000575.png\n"}
{"label": "resume", "path_img": "resume\\doc_000169.png\n"}
{"label": "paper", "path_img": "paper\\doc_000451.png\n"}
{"label": "paper", "path_img": "paper\\doc_000235.png\n"}
{"label": "paper", "path_img": "paper\\doc_000445.png\n"}
{"label": "paper", "path_img": "paper\\doc_000453.png\n"}
{"label": "email", "path_img": "email\\doc_000076.png\n"}
{"label": "email", "path_img": "email\\doc_000485.png\n"}
{"label": "paper", "path_img": "paper\\doc_000584.png\n"}
{"label": "email", "path_img": "email\\doc_000133.png\n"}
{"label": "paper", "path_img": "paper\\doc_000345.png\n"}
{"label": "email", "path_img": "email\\doc_000148.png\n"}
{"label": "paper", "path_img": "paper\\doc_000130.png\n"}
{"label": "email", "path_img": "email\\doc_000260.png\n"}
{"label": "email", "path_img": "email\\doc_000650.png\n"}
{"label": "resume", "path_img": "resume\\doc_000301.png\n"}
{"label": "paper", "path_img": "paper\\doc_000298.png\n"}
{"label": "paper", "path_img": "paper\\doc_000309.png\n"}
{"label": "email", "path_img": "email\\doc_000196.png\n"}
{"label": "email", "path_img": "email\\doc_000464.png\n"}
{"label": "paper", "path_img": "paper\\doc_000121.png\n"}
{"label": "paper", "path_img": "paper\\doc_000061.png\n"}
{"label": "resume", "path_img": "resume\\doc_000091.png\n"}
{"label": "email", "path_img": "email\\doc_000363.png\n"}
{"label": "resume", "path_img": "resume\\doc_000468.png\n"}
{"label": "paper", "path_img": "paper\\doc_000766.png\n"}
{"label": "email", "path_img": "email\\doc_000195.png\n"}
{"label": "resume", "path_img": "resume\\doc_000499.png\n"}
{"label": "email", "path_img": "email\\doc_000165.png\n"}
{"label": "email", "path_img": "email\\doc_000282.png\n"}
{"label": "resume", "path_img": "resume\\doc_000353.png\n"}
{"label": "email", "path_img": "email\\doc_000483.png\n"}
{"label": "resume", "path_img": "resume\\doc_000175.png\n"}
{"label": "email", "path_img": "email\\doc_000637.png\n"}
{"label": "paper", "path_img": "paper\\doc_000513.png\n"}
{"label": "email", "path_img": "email\\doc_000142.png\n"}
{"label": "email", "path_img": "email\\doc_000591.png\n"}
{"label": "resume", "path_img": "resume\\doc_000441.png\n"}
{"label": "resume", "path_img": "resume\\doc_000097.png\n"}
{"label": "email", "path_img": "email\\doc_000471.png\n"}
{"label": "email", "path_img": "email\\doc_000528.png\n"}
{"label": "email", "path_img": "email\\doc_000465.png\n"}
{"label": "email", "path_img": "email\\doc_000115.png\n"}
{"label": "paper", "path_img": "paper\\doc_000698.png\n"}
{"label": "email", "path_img": "email\\doc_000550.png\n"}
{"label": "resume", "path_img": "resume\\doc_000248.png\n"}
{"label": "paper", "path_img": "paper\\doc_000050.png\n"}
{"label": "paper", "path_img": "paper\\doc_000334.png\n"}
{"label": "email", "path_img": "email\\doc_000511.png\n"}
{"label": "email", "path_img": "email\\doc_000675.png\n"}
{"label": "resume", "path_img": "resume\\doc_000369.png\n"}
{"label": "email", "path_img": "email\\doc_000532.png\n"}
{"label": "email", "path_img": "email\\doc_000238.png\n"}
{"label": "email", "path_img": "email\\doc_000279.png\n"}
{"label": "email", "path_img": "email\\doc_000577.png\n"}
{"label": "resume", "path_img": "resume\\doc_000109.png\n"}
{"label": "paper", "path_img": "paper\\doc_000311.png\n"}
{"label": "resume", "path_img": "resume\\doc_000344.png\n"}
{"label": "email", "path_img": "email\\doc_000612.png\n"}
{"label": "email", "path_img": "email\\doc_000275.png\n"}
{"label": "resume", "path_img": "resume\\doc_000609.png\n"}
{"label": "resume", "path_img": "resume\\doc_000264.png\n"}
{"label": "email", "path_img": "email\\doc_000333.png\n"}
{"label": "resume", "path_img": "resume\\doc_000281.png\n"}
{"label": "paper", "path_img": "paper\\doc_000438.png\n"}
{"label": "paper", "path_img": "paper\\doc_000392.png\n"}
{"label": "resume", "path_img": "resume\\doc_000551.png\n"}
{"label": "resume", "path_img": "resume\\doc_000377.png\n"}
{"label": "paper", "path_img": "paper\\doc_000615.png\n"}
{"label": "paper", "path_img": "paper\\doc_000522.png\n"}
{"label": "resume", "path_img": "resume\\doc_000636.png\n"}
{"label": "resume", "path_img": "resume\\doc_000101.png\n"}
{"label": "paper", "path_img": "paper\\doc_000429.png\n"}
{"label": "email", "path_img": "email\\doc_000347.png\n"}
{"label": "email", "path_img": "email\\doc_000255.png\n"}
{"label": "resume", "path_img": "resume\\doc_000443.png\n"}
{"label": "resume", "path_img": "resume\\doc_000088.png\n"}
{"label": "paper", "path_img": "paper\\doc_000594.png\n"}
{"label": "resume", "path_img": "resume\\doc_000072.png\n"}
{"label": "resume", "path_img": "resume\\doc_000473.png\n"}
{"label": "paper", "path_img": "paper\\doc_000515.png\n"}
{"label": "resume", "path_img": "resume\\doc_000173.png\n"}
{"label": "email", "path_img": "email\\doc_000079.png\n"}
{"label": "resume", "path_img": "resume\\doc_000450.png\n"}
{"label": "resume", "path_img": "resume\\doc_000375.png\n"}
